Metadata-Version: 2.1
Name: mans_biblioteka
Version: 0.1
Summary: Mana fantastiskā bibliotēka!
Author: Jūsu vārds
Author-email: jusu@epasts.com
